Workbook
Name TaxRate: 'P&L Analysis'!$Q$2

Sheet Project Overview
A1: FINANCE PERFORMANCE & BUDGET ANALYSIS
A4: Portfolio project | 12-month illustrative dataset | Amounts in ₹ Lakhs
A6: Project Objective | B6: Evaluate revenue, profitability, operating-cost trends and budget performance over a 12-month period.
A7: Business Questions | B7: How did revenue and margins trend? Which months performed strongest/weakest? Did actual results meet budget?
A8: Analysis Built | B8: P&L analysis, gross/EBITDA/net margins, budget-vs-actual variance, monthly KPI analysis and management insights.
A9: Excel Skills Demonstrated | B9: SUM, MAX, MIN, INDEX/MATCH, percentage calculations, linked worksheets, conditional formatting and charts.
A10: Dataset Note | B10: Illustrative/synthetic dataset created for portfolio and learning purposes; it is not company-confidential data.
A11: Period | B11: April–March (12 months)
A18: Workbook Flow
A19: 1 | B19: Raw Data
A20: 2 | B20: P&L Analysis
A21: 3 | B21: Budget Variance
A22: 4 | B22: Monthly Analysis
A23: 5 | B23: Management Insights
A24: 6 | B24: Dashboard

Sheet Raw Data
A1: Month | B1: Revenue | C1: COGS | D1: Salaries | E1: Marketing | F1: Rent | G1: Utilities | H1: Other Opex | I1: Depreciation | J1: Interest | K1: Tax
A2: April | B2: 82 | C2: 47 | D2: 10 | E2: 5 | F2: 3 | G2: 1.2 | H2: 2.5 | I2: 1.5 | J2: 1 | K2: 2.5
A3: May | B3: 85 | C3: 48 | D3: 10 | E3: 5.5 | F3: 3 | G3: 1.2 | H3: 2.6 | I3: 1.5 | J3: 1 | K3: 2.6
A4: June | B4: 88 | C4: 49 | D4: 10.2 | E4: 6 | F4: 3 | G4: 1.3 | H4: 2.7 | I4: 1.5 | J4: 1 | K4: 2.7
A5: July | B5: 91 | C5: 51 | D5: 10.2 | E5: 6.2 | F5: 3 | G5: 1.3 | H5: 2.8 | I5: 1.5 | J5: 1 | K5: 2.8
A6: August | B6: 95 | C6: 52 | D6: 10.5 | E6: 6.5 | F6: 3 | G6: 1.4 | H6: 2.9 | I6: 1.5 | J6: 1 | K6: 3
A7: September | B7: 98 | C7: 54 | D7: 10.5 | E7: 7 | F7: 3 | G7: 1.4 | H7: 3 | I7: 1.5 | J7: 1 | K7: 3.1
A8: October | B8: 108 | C8: 58 | D8: 10.8 | E8: 9 | F8: 3.2 | G8: 1.5 | H8: 3.2 | I8: 1.5 | J8: 1.1 | K8: 3.5
A9: November | B9: 112 | C9: 59 | D9: 10.8 | E9: 8.5 | F9: 3.2 | G9: 1.5 | H9: 3.2 | I9: 1.5 | J9: 1.1 | K9: 3.7
A10: December | B10: 105 | C10: 57 | D10: 11 | E10: 7.5 | F10: 3.2 | G10: 1.5 | H10: 3.3 | I10: 1.5 | J10: 1.1 | K10: 3.4
A11: January | B11: 101 | C11: 55 | D11: 11 | E11: 6.8 | F11: 3.2 | G11: 1.5 | H11: 3.3 | I11: 1.5 | J11: 1.1 | K11: 3.2
A12: February | B12: 106 | C12: 57 | D12: 11.2 | E12: 7.2 | F12: 3.2 | G12: 1.6 | H12: 3.4 | I12: 1.5 | J12: 1.1 | K12: 3.4
A13: March | B13: 118 | C13: 62 | D13: 11.5 | E13: 8 | F13: 3.2 | G13: 1.6 | H13: 3.5 | I13: 1.5 | J13: 1.1 | K13: 3.9
A15: Note: | B15: Illustrative dataset; all financial amounts are in ₹ Lakhs.

Sheet P&L Analysis
B1: April | C1: May | D1: June | E1: July | F1: August | G1: September | H1: October | I1: November | J1: December | K1: January | L1: February | M1: March | P1: Assumptions
A2: Revenue | B2: ='Raw Data'!B2 | C2: ='Raw Data'!B3 | D2: ='Raw Data'!B4 | E2: ='Raw Data'!B5 | F2: ='Raw Data'!B6 | G2: ='Raw Data'!B7 | H2: ='Raw Data'!B8 | I2: ='Raw Data'!B9 | J2: ='Raw Data'!B10 | K2: ='Raw Data'!B11 | L2: ='Raw Data'!B12 | M2: ='Raw Data'!B13 | P2: Corporate Tax Rate | Q2: 0.2
A3: COGS | B3: ='Raw Data'!C2 | C3: ='Raw Data'!C3 | D3: ='Raw Data'!C4 | E3: ='Raw Data'!C5 | F3: ='Raw Data'!C6 | G3: ='Raw Data'!C7 | H3: ='Raw Data'!C8 | I3: ='Raw Data'!C9 | J3: ='Raw Data'!C10 | K3: ='Raw Data'!C11 | L3: ='Raw Data'!C12 | M3: ='Raw Data'!C13
A4: Gross Profit | B4: =B2-B3 | C4: =C2-C3 | D4: =D2-D3 | E4: =E2-E3 | F4: =F2-F3 | G4: =G2-G3 | H4: =H2-H3 | I4: =I2-I3 | ... M4: =M2-M3
A5: Gross Margin % | B5: =B4/B2 | C5: =C4/C2 | D5: =D4/D2 | E5: =E4/E2 | F5: =F4/F2 | G5: =G4/G2 | H5: =H4/H2 | I5: =I4/I2 | ... M5: =M4/M2
A6: Salaries | B6: ='Raw Data'!D2 | C6: ='Raw Data'!D3 | D6: ='Raw Data'!D4 | E6: ='Raw Data'!D5 | F6: ='Raw Data'!D6 | G6: ='Raw Data'!D7 | H6: ='Raw Data'!D8 | I6: ='Raw Data'!D9 | J6: ='Raw Data'!D10 | K6: ='Raw Data'!D11 | L6: ='Raw Data'!D12 | M6: ='Raw Data'!D13
A7: Marketing | B7: ='Raw Data'!E2 | C7: ='Raw Data'!E3 | D7: ='Raw Data'!E4 | E7: ='Raw Data'!E5 | F7: ='Raw Data'!E6 | G7: ='Raw Data'!E7 | H7: ='Raw Data'!E8 | I7: ='Raw Data'!E9 | J7: ='Raw Data'!E10 | K7: ='Raw Data'!E11 | L7: ='Raw Data'!E12 | M7: ='Raw Data'!E13
A8: Rent | B8: ='Raw Data'!F2 | C8: ='Raw Data'!F3 | D8: ='Raw Data'!F4 | E8: ='Raw Data'!F5 | F8: ='Raw Data'!F6 | G8: ='Raw Data'!F7 | H8: ='Raw Data'!F8 | I8: ='Raw Data'!F9 | J8: ='Raw Data'!F10 | K8: ='Raw Data'!F11 | L8: ='Raw Data'!F12 | M8: ='Raw Data'!F13
A9: Utilities | B9: ='Raw Data'!G2 | C9: ='Raw Data'!G3 | D9: ='Raw Data'!G4 | E9: ='Raw Data'!G5 | F9: ='Raw Data'!G6 | G9: ='Raw Data'!G7 | H9: ='Raw Data'!G8 | I9: ='Raw Data'!G9 | J9: ='Raw Data'!G10 | K9: ='Raw Data'!G11 | L9: ='Raw Data'!G12 | M9: ='Raw Data'!G13
A10: Other Operating Expenses | B10: ='Raw Data'!H2 | C10: ='Raw Data'!H3 | D10: ='Raw Data'!H4 | E10: ='Raw Data'!H5 | F10: ='Raw Data'!H6 | G10: ='Raw Data'!H7 | H10: ='Raw Data'!H8 | I10: ='Raw Data'!H9 | J10: ='Raw Data'!H10 | K10: ='Raw Data'!H11 | L10: ='Raw Data'!H12 | M10: ='Raw Data'!H13
A11: Total Operating Expenses | B11: =SUM(B6:B10) | C11: =SUM(C6:C10) | D11: =SUM(D6:D10) | E11: =SUM(E6:E10) | F11: =SUM(F6:F10) | G11: =SUM(G6:G10) | H11: =SUM(H6:H10) | I11: =SUM(I6:I10) | ... M11: =SUM(M6:M10)
A12: EBITDA | B12: =B4-B11 | C12: =C4-C11 | D12: =D4-D11 | E12: =E4-E11 | F12: =F4-F11 | G12: =G4-G11 | H12: =H4-H11 | I12: =I4-I11 | ... M12: =M4-M11
A13: EBITDA Margin % | B13: =B12/B2 | C13: =C12/C2 | D13: =D12/D2 | E13: =E12/E2 | F13: =F12/F2 | G13: =G12/G2 | H13: =H12/H2 | I13: =I12/I2 | ... M13: =M12/M2
A14: Depreciation | B14: ='Raw Data'!I2 | C14: ='Raw Data'!I3 | D14: ='Raw Data'!I4 | E14: ='Raw Data'!I5 | F14: ='Raw Data'!I6 | G14: ='Raw Data'!I7 | H14: ='Raw Data'!I8 | I14: ='Raw Data'!I9 | J14: ='Raw Data'!I10 | K14: ='Raw Data'!I11 | L14: ='Raw Data'!I12 | M14: ='Raw Data'!I13
A15: EBIT | B15: =B12-B14 | C15: =C12-C14 | D15: =D12-D14 | E15: =E12-E14 | F15: =F12-F14 | G15: =G12-G14 | H15: =H12-H14 | I15: =I12-I14 | ... M15: =M12-M14
A16: Interest | B16: ='Raw Data'!J2 | C16: ='Raw Data'!J3 | D16: ='Raw Data'!J4 | E16: ='Raw Data'!J5 | F16: ='Raw Data'!J6 | G16: ='Raw Data'!J7 | H16: ='Raw Data'!J8 | I16: ='Raw Data'!J9 | J16: ='Raw Data'!J10 | K16: ='Raw Data'!J11 | L16: ='Raw Data'!J12 | M16: ='Raw Data'!J13
A17: Profit Before Tax | B17: =B15-B16 | C17: =C15-C16 | D17: =D15-D16 | E17: =E15-E16 | F17: =F15-F16 | G17: =G15-G16 | H17: =H15-H16 | I17: =I15-I16 | ... M17: =M15-M16
A18: Tax (@ assumed rate) | B18: =ROUND(B17*TaxRate,2) | C18: =ROUND(C17*TaxRate,2) | D18: =ROUND(D17*TaxRate,2) | E18: =ROUND(E17*TaxRate,2) | F18: =ROUND(F17*TaxRate,2) | G18: =ROUND(G17*TaxRate,2) | H18: =ROUND(H17*TaxRate,2) | I18: =ROUND(I17*TaxRate,2) | ... M18: =ROUND(M17*TaxRate,2)
A19: Net Profit | B19: =B17-B18 | C19: =C17-C18 | D19: =D17-D18 | E19: =E17-E18 | F19: =F17-F18 | G19: =G17-G18 | H19: =H17-H18 | I19: =I17-I18 | ... M19: =M17-M18
A20: Net Profit Margin % | B20: =B19/B2 | C20: =C19/C2 | D20: =D19/D2 | E20: =E19/E2 | F20: =F19/F2 | G20: =G19/G2 | H20: =H19/H2 | I20: =I19/I2 | ... M20: =M19/M2

Sheet Budget Variance
A1: Metric | B1: Budget (₹ Lakhs) | C1: Actual (₹ Lakhs) | D1: Variance (₹ Lakhs) | E1: Variance % | F1: Interpretation
A2: Revenue | B2: 1150 | C2: =SUM('P&L Analysis'!B2:M2) | D2: =C2-B2 | E2: =D2/B2 | F2: [FAV] Revenue above budget
A3: COGS | B3: 630 | C3: =SUM('P&L Analysis'!B3:M3) | D3: =C3-B3 | E3: =D3/B3 | F3: [UNFAV] COGS above budget
A4: Gross Profit | B4: 520 | C4: =SUM('P&L Analysis'!B4:M4) | D4: =C4-B4 | E4: =D4/B4 | F4: [FAV] Gross Profit above budget
A5: Operating Expenses | B5: 275 | C5: =SUM('P&L Analysis'!B11:M11) | D5: =C5-B5 | E5: =D5/B5 | F5: [UNFAV] OpEx above budget -- key cost overrun
A6: EBITDA | B6: 245 | C6: =SUM('P&L Analysis'!B12:M12) | D6: =C6-B6 | E6: =D6/B6 | F6: [UNFAV] EBITDA below budget
A7: Net Profit | B7: 145 | C7: =SUM('P&L Analysis'!B19:M19) | D7: =C7-B7 | E7: =D7/B7 | F7: [FAV] Net Profit above budget
A8: OpEx as % of Revenue | B8: =B5/B2 | C8: =C5/C2 | D8: =C8-B8 | F8: [UNFAV] OpEx % exceeded budget -- headline risk
A9: Below-EBITDA Explanation | B9: Net Profit beat budget by +Rs25.1L (+17.3%) even though EBITDA missed by -Rs6.5L. Actual below-EBITDA costs: Depreciation Rs18.0L + Interest Rs12.6L + Tax Rs37.8L = Rs68.4L -- Rs31.6L below the Rs100L implied in the budget. The profit beat is a below-EBITDA cost windfall, NOT operational outperformance.
A11: Note: | B11: Positive variance is not automatically favorable: for Revenue/Profit it is generally favorable; for COGS/Operating Expenses it is generally unfavorable.

Sheet Monthly Analysis
A1: Month | B1: Revenue | C1: Gross Profit | D1: Gross Margin % | E1: EBITDA | F1: EBITDA Margin % | G1: Net Profit | H1: Net Profit Margin % | I1: OpEx as % of Revenue
A2: April | B2: 82 | C2: {=INDEX('P&L Analysis'!$B$4:$M$4,1,COLUMN(A1))} | D2: =C2/B2 | E2: ='P&L Analysis'!B12 | F2: =E2/B2 | G2: ='P&L Analysis'!B19 | H2: =G2/B2 | I2: ='P&L Analysis'!B11/'P&L Analysis'!B2
A3: May | B3: 85 | C3: {=INDEX('P&L Analysis'!$C$4:$M$4,1,COLUMN(A2))} | D3: =C3/B3 | E3: ='P&L Analysis'!C12 | F3: =E3/B3 | G3: ='P&L Analysis'!C19 | H3: =G3/B3 | I3: ='P&L Analysis'!C11/'P&L Analysis'!C2
A4: June | B4: 88 | C4: {=INDEX('P&L Analysis'!$D$4:$M$4,1,COLUMN(A3))} | D4: =C4/B4 | E4: ='P&L Analysis'!D12 | F4: =E4/B4 | G4: ='P&L Analysis'!D19 | H4: =G4/B4 | I4: ='P&L Analysis'!D11/'P&L Analysis'!D2
A5: July | B5: 91 | C5: {=INDEX('P&L Analysis'!$E$4:$M$4,1,COLUMN(A4))} | D5: =C5/B5 | E5: ='P&L Analysis'!E12 | F5: =E5/B5 | G5: ='P&L Analysis'!E19 | H5: =G5/B5 | I5: ='P&L Analysis'!E11/'P&L Analysis'!E2
A6: August | B6: 95 | C6: {=INDEX('P&L Analysis'!$F$4:$M$4,1,COLUMN(A5))} | D6: =C6/B6 | E6: ='P&L Analysis'!F12 | F6: =E6/B6 | G6: ='P&L Analysis'!F19 | H6: =G6/B6 | I6: ='P&L Analysis'!F11/'P&L Analysis'!F2
A7: September | B7: 98 | C7: {=INDEX('P&L Analysis'!$G$4:$M$4,1,COLUMN(A6))} | D7: =C7/B7 | E7: ='P&L Analysis'!G12 | F7: =E7/B7 | G7: ='P&L Analysis'!G19 | H7: =G7/B7 | I7: ='P&L Analysis'!G11/'P&L Analysis'!G2
A8: October | B8: 108 | C8: {=INDEX('P&L Analysis'!$H$4:$M$4,1,COLUMN(A7))} | D8: =C8/B8 | E8: ='P&L Analysis'!H12 | F8: =E8/B8 | G8: ='P&L Analysis'!H19 | H8: =G8/B8 | I8: ='P&L Analysis'!H11/'P&L Analysis'!H2
A9: November | B9: 112 | C9: {=INDEX('P&L Analysis'!$I$4:$M$4,1,COLUMN(A8))} | D9: =C9/B9 | E9: ='P&L Analysis'!I12 | F9: =E9/B9 | G9: ='P&L Analysis'!I19 | H9: =G9/B9 | I9: ='P&L Analysis'!I11/'P&L Analysis'!I2
A10: December | B10: 105 | C10: {=INDEX('P&L Analysis'!$J$4:$M$4,1,COLUMN(A9))} | D10: =C10/B10 | E10: ='P&L Analysis'!J12 | F10: =E10/B10 | G10: ='P&L Analysis'!J19 | H10: =G10/B10 | I10: ='P&L Analysis'!J11/'P&L Analysis'!J2
A11: January | B11: 101 | C11: {=INDEX('P&L Analysis'!$K$4:$M$4,1,COLUMN(A10))} | D11: =C11/B11 | E11: ='P&L Analysis'!K12 | F11: =E11/B11 | G11: ='P&L Analysis'!K19 | H11: =G11/B11 | I11: ='P&L Analysis'!K11/'P&L Analysis'!K2
A12: February | B12: 106 | C12: {=INDEX('P&L Analysis'!$L$4:$M$4,1,COLUMN(A11))} | D12: =C12/B12 | E12: ='P&L Analysis'!L12 | F12: =E12/B12 | G12: ='P&L Analysis'!L19 | H12: =G12/B12 | I12: ='P&L Analysis'!L11/'P&L Analysis'!L2
A13: March | B13: 118 | C13: {=INDEX('P&L Analysis'!$M$4:$M$4,1,COLUMN(A12))} | D13: =C13/B13 | E13: ='P&L Analysis'!M12 | F13: =E13/B13 | G13: ='P&L Analysis'!M19 | H13: =G13/B13 | I13: ='P&L Analysis'!M11/'P&L Analysis'!M2

Sheet Management Insights
A1: Insight | B1: Method / Formula | C1: Result | D1: Business Interpretation
A2: Highest Revenue | B2: MAX(Monthly Analysis!B2:B13) | C2: =MAX('Monthly Analysis'!B2:B13) | D2: March records the highest monthly revenue.
A3: Lowest Revenue | B3: MIN(Monthly Analysis!B2:B13) | C3: =MIN('Monthly Analysis'!B2:B13) | D3: April records the lowest monthly revenue.
A4: Highest Revenue Month | B4: INDEX + MATCH | C4: =INDEX('Monthly Analysis'!A2:A13,MATCH(C2,'Monthly Analysis'!B2:B13,0)) | D4: Identifies the month associated with peak revenue.
A5: Lowest Revenue Month | B5: INDEX + MATCH | C5: =INDEX('Monthly Analysis'!A2:A13,MATCH(C3,'Monthly Analysis'!B2:B13,0)) | D5: Identifies the month associated with lowest revenue.
A6: Revenue Growth (Endpoint: March vs April) | B6: (March − April) / April | C6: =('Monthly Analysis'!B13-'Monthly Analysis'!B2)/'Monthly Analysis'!B2 | D6: Cumulative period-end growth (March vs April). Not a trend measure -- see 'Avg MoM Growth' below for a more defensible metric.
A7: Avg Month-on-Month Revenue Growth | B7: Geometric: (Mar/Apr)^(1/11) - 1 | C7: =('Monthly Analysis'!B13/'Monthly Analysis'!B2)^(1/11)-1 | D7: Compound monthly growth rate over 11 intervals (~3.4%). More defensible than a two-point comparison. Indicates steady organic revenue growth across the year.
A8: Gross Margin Change | B8: March GM − April GM | C8: ='Monthly Analysis'!D13-'Monthly Analysis'!D2 | D8: Margin improved over the period.
A9: EBITDA Margin Change | B9: March EBITDA margin − April EBITDA margin | C9: ='Monthly Analysis'!F13-'Monthly Analysis'!F2 | D9: Operating profitability improved over the period.
A10: Net Profit Margin Change | B10: March NP margin − April NP margin | C10: ='Monthly Analysis'!H13-'Monthly Analysis'!H2 | D10: Bottom-line margin improved over the period.
A11: Budget Revenue Variance | B11: Actual − Budget | C11: ='Budget Variance'!D2 | D11: Revenue finished above budget.
A12: Budget EBITDA Variance | B12: Actual − Budget | C12: ='Budget Variance'!D6 | D12: EBITDA finished below budget despite higher revenue.
A13: Budget Net Profit Variance | B13: Actual − Budget | C13: ='Budget Variance'!D7 | D13: Net profit finished above budget.

Sheet Dashboard
A1: FINANCIAL PERFORMANCE DASHBOARD
A3: 12-Month Management View | Illustrative Dataset | ₹ Lakhs
A5: Revenue | D5: Gross Margin (Full Year) | G5: EBITDA | J5: Net Profit
A6: ='Budget Variance'!C2 | D6: ='Budget Variance'!C4/'Budget Variance'!C2 | G6: ='Budget Variance'!C6 | J6: ='Budget Variance'!C7
G25: HEADLINE: OpEx exceeded budget by +9.6% vs revenue growth of +3.4% — this dragged EBITDA below budget despite top-line expansion.
G26: Revenue rose from Rs82L (April) to Rs118L (March); avg. month-on-month growth ~3.5% (compound).
G27: Gross margin improved from 42.7% to 47.5%; full-year gross margin: 45.4%.
G28: EBITDA margin improved from 16.2% to 23.9%; full-year EBITDA margin: 20.1%.
G29: Revenue exceeded budget by Rs39L (+3.4%); EBITDA missed budget by Rs6.5L (-2.6%).
G30: Net profit beat budget by Rs25.1L (+17.3%) — NOT from trading: below-EBITDA costs (Depr Rs18L + Interest Rs12.6L + Tax Rs37.8L = Rs68.4L) were Rs31.6L below the implied Rs100L budget allowance.
G31: OpEx as % of Revenue: budget implied ~23.9%; actual 25.4% — a headline metric to watch.
